exam_marking/__init__.py
exam_marking/routes.py
exam_marking/templates/index.html
exam_marking-0.0.10.dist-info/METADATA
exam_marking-0.0.10.dist-info/WHEEL
exam_marking-0.0.10.dist-info/entry_points.txt
exam_marking-0.0.10.dist-info/licenses/LICENSE
exam_marking-0.0.10.dist-info/RECORD
