Metadata-Version: 2.3
Name: exam-marking
Version: 0.0.10
Summary: A tool to ease UNSW exam marking (COMP6841 in particular).
Project-URL: Repository, https://github.com/HamishWHC/exam-marking.git
Project-URL: Issues, https://github.com/HamishWHC/exam-marking/issues
Author-email: Hamish Cox <hamish@hamishwhc.com>
Maintainer-email: Hamish Cox <hamish@hamishwhc.com>
License: Copyright © 2024 Hamish Cox
Classifier: Development Status :: 4 - Beta
Classifier: Environment :: Console
Classifier: Intended Audience :: Education
Classifier: Intended Audience :: End Users/Desktop
Classifier: License :: OSI Approved :: MIT License
Classifier: Operating System :: MacOS
Classifier: Operating System :: Microsoft :: Windows
Classifier: Operating System :: POSIX :: Linux
Classifier: Programming Language :: Python :: 3
Classifier: Programming Language :: Python :: 3 :: Only
Classifier: Programming Language :: Python :: 3.9
Classifier: Programming Language :: Python :: 3.10
Classifier: Programming Language :: Python :: 3.11
Classifier: Programming Language :: Python :: 3.12
Classifier: Topic :: Utilities
Requires-Python: >=3.9
Requires-Dist: click>=8.1.7
Requires-Dist: flask>=3.1.0
